[{"pk": 1, "model": "elebox.corpus", "fields": {"draft": "pics/corps/ECJ_Series_0805_1.40.jpg", "name": "0805"}}, {"pk": 2, "model": "elebox.corpus", "fields": {"draft": "pics/corps/0201.jpg", "name": "0201"}}, {"pk": 3, "model": "elebox.corpus", "fields": {"draft": "pics/corps/0402.jpg", "name": "0402"}}, {"pk": 4, "model": "elebox.corpus", "fields": {"draft": "pics/corps/0603.jpg", "name": "0603"}}, {"pk": 5, "model": "elebox.corpus", "fields": {"draft": "pics/corps/1206.jpg", "name": "1206"}}, {"pk": 6, "model": "elebox.corpus", "fields": {"draft": "pics/corps/1210.jpg", "name": "1210"}}, {"pk": 7, "model": "elebox.corpus", "fields": {"draft": "pics/corps/1812.jpg", "name": "1812"}}, {"pk": 8, "model": "elebox.corpus", "fields": {"draft": "pics/corps/1825.jpeg", "name": "1825"}}, {"pk": 9, "model": "elebox.corpus", "fields": {"draft": "pics/corps/2220.jpg", "name": "2220"}}, {"pk": 10, "model": "elebox.corpus", "fields": {"draft": "pics/corps/2225.jpg", "name": "2225"}}, {"pk": 11, "model": "elebox.corpus", "fields": {"draft": "pics/corps/hc49u.jpeg", "name": "HC49U"}}]